debug.py
clappform/__init__.py
clappform/dataclasses.py
clappform/exceptions.py
clappform-4.1.0.dist-info/LICENSE
clappform-4.1.0.dist-info/METADATA
clappform-4.1.0.dist-info/WHEEL
clappform-4.1.0.dist-info/top_level.txt
clappform-4.1.0.dist-info/RECORD
