Metadata-Version: 2.1
Name: clappform
Version: 4.1.0
Summary: Clappform Python API wrapper
Author-email: "Clappform B.V." <info@clappform.com>
Project-URL: Documentation, https://clappform.readthedocs.io
Project-URL: Source, https://github.com/ClappFormOrg/clappform-python
Classifier: Development Status :: 5 - Production/Stable
Classifier: License :: OSI Approved :: MIT License
Classifier: Programming Language :: Python :: 3
Classifier: Operating System :: OS Independent
Requires-Python: >=3.10
License-File: LICENSE
Requires-Dist: requests ==2.31.0
Requires-Dist: Cerberus ==1.3.4
Requires-Dist: pandas ==1.5.2
